nexgen/__init__.py
nexgen/__main__.py
nexgen/log.py
nexgen/utils.py
nexgen/beamlines/ED_params.py
nexgen/beamlines/ED_singla_nxs.py
nexgen/beamlines/I19_2_gda_nxs.py
nexgen/beamlines/I19_2_nxs.py
nexgen/beamlines/I19_2_params.py
nexgen/beamlines/I24_params.py
nexgen/beamlines/SSX_Eiger_nxs.py
nexgen/beamlines/SSX_chip.py
nexgen/beamlines/SSX_expt.py
nexgen/beamlines/__init__.py
nexgen/beamlines/beamline_utils.py
nexgen/beamlines/GDAtools/ExtendedRequest.py
nexgen/beamlines/GDAtools/GDAjson2params.py
nexgen/beamlines/GDAtools/__init__.py
nexgen/command_line/ED_mrc_to_nexus.py
nexgen/command_line/ED_nexus.py
nexgen/command_line/I19_2_cli.py
nexgen/command_line/SSX_cli.py
nexgen/command_line/__init__.py
nexgen/command_line/cli_config.py
nexgen/command_line/compare_pcap.py
nexgen/command_line/nexus_generator.py
nexgen/command_line/parse_utils.py
nexgen/nxs_copy/__init__.py
nexgen/nxs_copy/copy_nexus.py
nexgen/nxs_copy/copy_tristan_nexus.py
nexgen/nxs_copy/copy_utils.py
nexgen/nxs_utils/__init__.py
nexgen/nxs_utils/axes.py
nexgen/nxs_utils/detector.py
nexgen/nxs_utils/goniometer.py
nexgen/nxs_utils/sample.py
nexgen/nxs_utils/scan_utils.py
nexgen/nxs_utils/source.py
nexgen/nxs_write/__init__.py
nexgen/nxs_write/ed_nxmx_writer.py
nexgen/nxs_write/nxclass_writers.py
nexgen/nxs_write/nxmx_writer.py
nexgen/nxs_write/write_utils.py
nexgen/tools/__init__.py
nexgen/tools/constants.py
nexgen/tools/data_writer.py
nexgen/tools/ed_tools.py
nexgen/tools/meta_reader.py
nexgen/tools/metafile.py
nexgen/tools/mrc_tools.py
nexgen/tools/vds_tools.py
nexgen-0.11.2.dist-info/licenses/LICENSE
nexgen-0.11.2.dist-info/METADATA
nexgen-0.11.2.dist-info/WHEEL
nexgen-0.11.2.dist-info/entry_points.txt
nexgen-0.11.2.dist-info/top_level.txt
nexgen-0.11.2.dist-info/RECORD
