Metadata-Version: 2.4
Name: nexgen
Version: 0.11.2
Summary: Next Generation Nexus Generator
Author-email: Diamond Light Source - Scientific Software <scientificsoftware@diamond.ac.uk>
License: BSD 3-Clause License
Project-URL: GitHub, https://github.com/DiamondLightSource/nexgen
Project-URL: Documentation, https://nexgen.readthedocs.io/
Project-URL: Bug-Tracker, https://github.com/DiamondLightSource/nexgen/issues
Keywords: nexus,NXmx
Classifier: Development Status :: 3 - Alpha
Classifier: Intended Audience :: Developers
Classifier: License :: OSI Approved :: BSD License
Classifier: Natural Language :: English
Classifier: Programming Language :: Python :: 3.11
Classifier: Programming Language :: Python :: 3.12
Requires-Python: >=3.11
License-File: LICENSE
Requires-Dist: h5py
Requires-Dist: hdf5plugin>=4.0.1
Requires-Dist: numpy
Requires-Dist: pint>=0.24.4
Requires-Dist: importlib_resources>=1.1
Requires-Dist: scanspec
Requires-Dist: pydantic
Requires-Dist: mrcfile>=1.5.3
Requires-Dist: PyYAML>=6.0.2
Provides-Extra: dev
Requires-Dist: black; extra == "dev"
Requires-Dist: ruff; extra == "dev"
Requires-Dist: pytest; extra == "dev"
Requires-Dist: pytest-cov; extra == "dev"
Requires-Dist: pytest-random-order; extra == "dev"
Requires-Dist: sphinx-autobuild; extra == "dev"
Requires-Dist: sphinx-rtd-theme; extra == "dev"
Requires-Dist: autodoc_pydantic; extra == "dev"
Requires-Dist: bump-my-version; extra == "dev"
Requires-Dist: ipython; extra == "dev"
Requires-Dist: mockito; extra == "dev"
Requires-Dist: pre-commit; extra == "dev"
Requires-Dist: pipdeptree; extra == "dev"
Requires-Dist: mypy; extra == "dev"
Requires-Dist: tox; extra == "dev"
Requires-Dist: wheel; extra == "dev"
Requires-Dist: build; extra == "dev"
Requires-Dist: types-mock; extra == "dev"
Dynamic: license-file
